{
  "id": "webgfx-103_phi-3-mini-4k-instruct_ort_webgpu",
  "client": "webgfx-103",
  "model": "Phi-3-mini-4k-instruct",
  "runtime": "ort",
  "backend": "webgpu",
  "results": [
    {
      "pl": 128,
      "tg": 128,
      "ttftMs": 74.85,
      "plTs": 1709.97,
      "tgTs": 144.16,
      "e2eMs": 941.97
    },
    {
      "pl": 256,
      "tg": 128,
      "ttftMs": 122.91,
      "plTs": 2082.83,
      "tgTs": 143.67,
      "e2eMs": 992.96
    }
  ],
  "system": {
    "timestamp": "2026-04-16T12:33:41.596269",
    "os": "Windows 11",
    "cpu": "AMD64 Family 26 Model 68 Stepping 0, AuthenticAMD",
    "hostname": "webgfx-103",
    "gpu": "AMD Radeon(TM) Graphics, AMD Radeon RX 7900 XTX"
  },
  "sourceResultId": "stdin",
  "createdAt": "2026-04-16T04:49:30.559Z"
}